{
  "last_updated": "2026-02-15T18:23:55.127791",
  "waitlists": {
    "2s - TALENTED 2s / F 9:15": [
      {
        "position": 1,
        "name": "Hoelscher, Hannah"
      },
      {
        "position": 2,
        "name": "Redmond, June"
      },
      {
        "position": 3,
        "name": "Palmer, Evelyn"
      }
    ],
    "2s - TALENTED 2s / S 9:15": [
      {
        "position": 1,
        "name": "Zaragoza, Bennett"
      },
      {
        "position": 2,
        "name": "Loken, Lucy"
      }
    ],
    "2s - WONDERFUL WALKERS / TALENTED 2S (COMBO) / F 11:15": [
      {
        "position": 1,
        "name": "Sigdahl, Greta"
      },
      {
        "position": 2,
        "name": "Vortherms, Brooks"
      },
      {
        "position": 3,
        "name": "Anderson, Aria"
      },
      {
        "position": 4,
        "name": "Solberg, Birdie"
      },
      {
        "position": 5,
        "name": "Minger, Toren"
      },
      {
        "position": 6,
        "name": "Minger, Talvi"
      },
      {
        "position": 7,
        "name": "Redmond, June"
      },
      {
        "position": 8,
        "name": "Christiansen, Sage"
      }
    ],
    "3/4s - TREMENDOUS 3s/FABULOUS 4s (COMBO) F 9:15": [
      {
        "position": 1,
        "name": "Stoneburner, Harrison"
      },
      {
        "position": 2,
        "name": "Howells, Andi"
      },
      {
        "position": 3,
        "name": "Redmond, Isla"
      },
      {
        "position": 4,
        "name": "Gruenhagen , Georgie"
      },
      {
        "position": 5,
        "name": "Hoelscher, Henley"
      }
    ],
    "3/4s - TREMENDOUS 3s/FABULOUS 4s (COMBO) F 10:15": [
      {
        "position": 1,
        "name": "Stoneburner, Harrison"
      },
      {
        "position": 2,
        "name": "Howells, Andi"
      }
    ],
    "3/4s - TREMENDOUS 3s/FABULOUS 4s (COMBO) F 11:15": [
      {
        "position": 1,
        "name": "Howells, Andi"
      },
      {
        "position": 2,
        "name": "Redmond, Isla"
      }
    ],
    "3/4s - TREMENDOUS 3s/FABULOUS 4s (COMBO) F 4:15": [
      {
        "position": 1,
        "name": "Timcho, Kyle"
      },
      {
        "position": 2,
        "name": "Kramin, Evelyn"
      },
      {
        "position": 3,
        "name": "Vitense , Abigail"
      },
      {
        "position": 4,
        "name": "Loge, Ingrid"
      },
      {
        "position": 5,
        "name": "Reynolds, Macklan"
      }
    ],
    "3/4s - TREMENDOUS 3s/FABULOUS 4s (COMBO) F 5:15": [
      {
        "position": 1,
        "name": "Carlson, Wren"
      },
      {
        "position": 2,
        "name": "Hoffman , Lyra"
      },
      {
        "position": 3,
        "name": "Redmond, Isla"
      },
      {
        "position": 4,
        "name": "Mahrer, Lincoln"
      },
      {
        "position": 5,
        "name": "Loge, Ingrid"
      },
      {
        "position": 6,
        "name": "Stencel, Camden"
      }
    ],
    "3/4s - TREMENDOUS 3s/FABULOUS 4s (COMBO) M 5:15": [
      {
        "position": 1,
        "name": "Miller, Kennedy"
      },
      {
        "position": 2,
        "name": "Anthony, Asher"
      },
      {
        "position": 3,
        "name": "Riedel, Mia"
      },
      {
        "position": 4,
        "name": "Hubler, Amelia"
      },
      {
        "position": 5,
        "name": "Hewitt, India"
      },
      {
        "position": 6,
        "name": "Ruehl, Callie"
      },
      {
        "position": 7,
        "name": "Walker, Penny"
      },
      {
        "position": 8,
        "name": "Eddie, Dax"
      },
      {
        "position": 9,
        "name": "Armbrust, Caroline"
      },
      {
        "position": 10,
        "name": "Hegedus, Nora"
      },
      {
        "position": 11,
        "name": "Dunlay, Ellie"
      },
      {
        "position": 12,
        "name": "Amundson, Sunny"
      },
      {
        "position": 13,
        "name": "Kaliszewski, Brynley"
      },
      {
        "position": 14,
        "name": "Niederman, Lara"
      },
      {
        "position": 15,
        "name": "Harwood, Lucy"
      },
      {
        "position": 16,
        "name": "Ackmann, Harrison"
      },
      {
        "position": 17,
        "name": "leanger, Summer jo"
      },
      {
        "position": 18,
        "name": "Loge, Ingrid"
      }
    ],
    "3/4s - TREMENDOUS 3s/FABULOUS 4s (COMBO) M 6:15": [
      {
        "position": 1,
        "name": "Sufka, Nellie"
      },
      {
        "position": 2,
        "name": "Hubler, Amelia"
      },
      {
        "position": 3,
        "name": "Ruehl, Callie"
      },
      {
        "position": 4,
        "name": "Peterson, Noa"
      },
      {
        "position": 5,
        "name": "Hughes, Wesley"
      },
      {
        "position": 6,
        "name": "Walker, Penny"
      },
      {
        "position": 7,
        "name": "Hewitt, India"
      },
      {
        "position": 8,
        "name": "Burnham, Evelyn"
      },
      {
        "position": 9,
        "name": "Kallas, Quinn"
      },
      {
        "position": 10,
        "name": "Kaliszewski, Brynley"
      },
      {
        "position": 11,
        "name": "Harwood, Lucy"
      },
      {
        "position": 12,
        "name": "Holman, Eliana"
      },
      {
        "position": 13,
        "name": "O'Loughlin, Raya"
      },
      {
        "position": 14,
        "name": "Kenady, Liliana"
      },
      {
        "position": 15,
        "name": "Loge, Ingrid"
      }
    ],
    "3/4s - TREMENDOUS 3s/FABULOUS 4s (COMBO) S 10:15": [
      {
        "position": 1,
        "name": "Naughtin, Eve"
      },
      {
        "position": 2,
        "name": "Walker, Penny"
      },
      {
        "position": 3,
        "name": "Anderson, Margot"
      },
      {
        "position": 4,
        "name": "Hegedus, Nora"
      },
      {
        "position": 5,
        "name": "Simmons, Brynne"
      },
      {
        "position": 6,
        "name": "Phillips, Elle"
      },
      {
        "position": 7,
        "name": "Krause, Collins"
      },
      {
        "position": 8,
        "name": "Rubi, Daisy"
      },
      {
        "position": 9,
        "name": "Hewitt, Camilla"
      },
      {
        "position": 10,
        "name": "Stickney, Ollie"
      },
      {
        "position": 11,
        "name": "Phillips, Dane"
      },
      {
        "position": 12,
        "name": "Hoffarber, Wren"
      },
      {
        "position": 13,
        "name": "Kaliszewski, Brynley"
      },
      {
        "position": 14,
        "name": "Anderson, Margaret"
      },
      {
        "position": 15,
        "name": "Pederson, Jacob"
      },
      {
        "position": 16,
        "name": "Skjonsby, Violet"
      },
      {
        "position": 17,
        "name": "Timcho, Kyle"
      },
      {
        "position": 18,
        "name": "Mifek, Eloise"
      },
      {
        "position": 19,
        "name": "Redmond, Isla"
      },
      {
        "position": 20,
        "name": "Hewitt, India"
      },
      {
        "position": 21,
        "name": "Hubler, Amelia"
      },
      {
        "position": 22,
        "name": "Cadwallader , Baker"
      },
      {
        "position": 23,
        "name": "Mahrer, Lincoln"
      }
    ],
    "3/4s - TREMENDOUS 3s/FABULOUS 4s (COMBO) T 5:15": [
      {
        "position": 1,
        "name": "Ortlip, Callen"
      },
      {
        "position": 2,
        "name": "Ackmann, Harrison"
      },
      {
        "position": 3,
        "name": "Bloomer, Mackenzie"
      },
      {
        "position": 4,
        "name": "Wickesberg, Harper"
      },
      {
        "position": 5,
        "name": "Christel , Oliver"
      },
      {
        "position": 6,
        "name": "Loge, Ingrid"
      },
      {
        "position": 7,
        "name": "Keegan, Mavis"
      },
      {
        "position": 8,
        "name": "Carlson, Wren"
      }
    ],
    "3/4s - TREMENDOUS 3s/FABULOUS 4s (COMBO) T 6:15": [
      {
        "position": 1,
        "name": "Kaliszewski, Brynley"
      },
      {
        "position": 2,
        "name": "Amundson, Sunny"
      },
      {
        "position": 3,
        "name": "Thompson, Lola"
      },
      {
        "position": 4,
        "name": "DeBoer, Theo"
      },
      {
        "position": 5,
        "name": "Hewitt, India"
      },
      {
        "position": 6,
        "name": "Hubler, Amelia"
      },
      {
        "position": 7,
        "name": "Redmond, Isla"
      },
      {
        "position": 8,
        "name": "Kenady, Liliana"
      },
      {
        "position": 9,
        "name": "Loge, Ingrid"
      }
    ],
    "3/4s - TREMENDOUS 3s/FABULOUS 4s (COMBO) T 9:15": [
      {
        "position": 1,
        "name": "Darley, Bayleigh"
      },
      {
        "position": 2,
        "name": "Bichanich , Carter"
      }
    ],
    "3/4s - TREMENDOUS 3s/FABULOUS 4s (COMBO) TH 6:15": [
      {
        "position": 1,
        "name": "Bloomer, Mackenzie"
      },
      {
        "position": 2,
        "name": "Halloran, Lillian"
      },
      {
        "position": 3,
        "name": "Fraser, Quinnlyn"
      },
      {
        "position": 4,
        "name": "Loge, Ingrid"
      }
    ],
    "3/4s - TREMENDOUS 3s/FABULOUS 4s (COMBO) W 4:15": [
      {
        "position": 1,
        "name": "Pitts, Penelope"
      },
      {
        "position": 2,
        "name": "leanger, Summer jo"
      },
      {
        "position": 3,
        "name": "Prudden, Poppy"
      }
    ],
    "3/4s - TREMENDOUS 3s/FABULOUS 4s (COMBO) W 5:15": [
      {
        "position": 1,
        "name": "House, Scarlett"
      },
      {
        "position": 2,
        "name": "Sallstrom, Hadley"
      },
      {
        "position": 3,
        "name": "Hewitt, India"
      },
      {
        "position": 4,
        "name": "Hubler, Amelia"
      },
      {
        "position": 5,
        "name": "Jensen, Nolan"
      },
      {
        "position": 6,
        "name": "Armbrust, Caroline"
      },
      {
        "position": 7,
        "name": "Stormoen , Charlotte"
      },
      {
        "position": 8,
        "name": "Hegedus, Nora"
      },
      {
        "position": 9,
        "name": "Olson, Annika"
      },
      {
        "position": 10,
        "name": "Abbott, Lucia"
      },
      {
        "position": 11,
        "name": "Erickson, Ardis"
      },
      {
        "position": 12,
        "name": "Dunlay, Ellie"
      },
      {
        "position": 13,
        "name": "Amundson, Sunny"
      },
      {
        "position": 14,
        "name": "Stencel, Camden"
      },
      {
        "position": 15,
        "name": "Carlson, Wren"
      }
    ],
    "ADVANCED / M 6:30": [
      {
        "position": 1,
        "name": "Shah, Pari"
      },
      {
        "position": 2,
        "name": "Lahti, Zoe"
      },
      {
        "position": 3,
        "name": "Smith, Emily"
      },
      {
        "position": 4,
        "name": "Jaster, Evelyn"
      }
    ],
    "ADVANCED / TH 4:00": [
      {
        "position": 1,
        "name": "Solberg, Sage"
      },
      {
        "position": 2,
        "name": "Schultz, Charlotte"
      },
      {
        "position": 3,
        "name": "Finck, Aleila"
      },
      {
        "position": 4,
        "name": "Freedland, Samantha"
      }
    ],
    "ADVANCED BEGINNER /M 5:15": [
      {
        "position": 1,
        "name": "Kiecker, Josie"
      },
      {
        "position": 2,
        "name": "Olson , Emerson"
      },
      {
        "position": 3,
        "name": "Wille , Lainey"
      },
      {
        "position": 4,
        "name": "Hubler, Nora"
      },
      {
        "position": 5,
        "name": "Simmons, Jordyn"
      },
      {
        "position": 6,
        "name": "Femling, Lennon"
      },
      {
        "position": 7,
        "name": "Lideen, Mae"
      }
    ],
    "ADVANCED BEGINNER /M 6:30": [
      {
        "position": 1,
        "name": "Fredriksson, Grace"
      }
    ],
    "ADVANCED BEGINNER /T 5:15": [
      {
        "position": 1,
        "name": "Corcoran , Blake"
      },
      {
        "position": 2,
        "name": "Athayde, Brynn"
      },
      {
        "position": 3,
        "name": "Kinzie, Claire"
      },
      {
        "position": 4,
        "name": "Christel , Eleanor"
      },
      {
        "position": 5,
        "name": "Kallas, Piper"
      },
      {
        "position": 6,
        "name": "Bateman, Olivia"
      },
      {
        "position": 7,
        "name": "Koenen, Courtney"
      },
      {
        "position": 8,
        "name": "Olson , Emerson"
      }
    ],
    "ADVANCED BEGINNER /TH 4:00": [
      {
        "position": 1,
        "name": "Goodman, Ryla"
      },
      {
        "position": 2,
        "name": "Wille , Lainey"
      },
      {
        "position": 3,
        "name": "Beimers, Charlotte"
      }
    ],
    "ADVANCED BEGINNER /TH 5:15": [
      {
        "position": 1,
        "name": "Wille , Lainey"
      },
      {
        "position": 2,
        "name": "Rock, Sienna"
      },
      {
        "position": 3,
        "name": "Holman, Aurora"
      }
    ],
    "ADVANCED BEGINNER /TH 6:30": [
      {
        "position": 1,
        "name": "Wildenberg, Paige"
      },
      {
        "position": 2,
        "name": "Hutchinson, Josephine"
      },
      {
        "position": 3,
        "name": "Wille , Lainey"
      },
      {
        "position": 4,
        "name": "Fredriksson, Grace"
      }
    ],
    "ADVANCED BEGINNER /W 6:30": [
      {
        "position": 1,
        "name": "Lillehaug, Claire"
      },
      {
        "position": 2,
        "name": "Gregg, Maren"
      },
      {
        "position": 3,
        "name": "Fredriksson, Grace"
      }
    ],
    "BEGINNER / ADVANCED BEGINNER (COMBO) / S 9:00": [
      {
        "position": 1,
        "name": "Bucka, Lylith"
      },
      {
        "position": 2,
        "name": "Snell, Nina"
      },
      {
        "position": 3,
        "name": "Molnar, Emma"
      },
      {
        "position": 4,
        "name": "Anderson, Addison"
      },
      {
        "position": 5,
        "name": "Timcho, Marnie"
      },
      {
        "position": 6,
        "name": "Thornburg , Holly"
      },
      {
        "position": 7,
        "name": "Phillips, Elle"
      }
    ],
    "BEGINNER / M 6:30": [
      {
        "position": 1,
        "name": "Kretzmann, Brynlee"
      },
      {
        "position": 2,
        "name": "Berg, Georgie"
      },
      {
        "position": 3,
        "name": "Olsem, Brooke"
      },
      {
        "position": 4,
        "name": "Thayer, Ava"
      },
      {
        "position": 5,
        "name": "Thayer, Evelyn"
      },
      {
        "position": 6,
        "name": "O'Loughlin, Ella"
      },
      {
        "position": 7,
        "name": "White, Emilia"
      }
    ],
    "BEGINNER / S 11:30": [
      {
        "position": 1,
        "name": "Thornburg , Holly"
      },
      {
        "position": 2,
        "name": "Simson, Everly"
      },
      {
        "position": 3,
        "name": "Fleming, Davie"
      },
      {
        "position": 4,
        "name": "Snell, Nina"
      }
    ],
    "BEGINNER / TH 6:30": [
      {
        "position": 1,
        "name": "Thayer, Evelyn"
      },
      {
        "position": 2,
        "name": "Thayer, Ava"
      },
      {
        "position": 3,
        "name": "White, Emilia"
      }
    ],
    "BEGINNER / W 5:15": [
      {
        "position": 1,
        "name": "Kreatz, Hazel"
      },
      {
        "position": 2,
        "name": "Elenkiwich, Matilda"
      },
      {
        "position": 3,
        "name": "Harker, Annelise"
      },
      {
        "position": 4,
        "name": "Ferezy, Louise"
      },
      {
        "position": 5,
        "name": "Jepson, Cora"
      },
      {
        "position": 6,
        "name": "Berding, Monroe"
      },
      {
        "position": 7,
        "name": "Snell, Nina"
      },
      {
        "position": 8,
        "name": "Spalding , Lilliana"
      },
      {
        "position": 9,
        "name": "Spalding , Scarlett"
      },
      {
        "position": 10,
        "name": "Napravnik, Ava"
      },
      {
        "position": 11,
        "name": "Olson, Lyla"
      },
      {
        "position": 12,
        "name": "Buckland, Bella"
      },
      {
        "position": 13,
        "name": "Stencel, Josslyn"
      }
    ],
    "BOYS BEGINNER / T 5:15": [
      {
        "position": 1,
        "name": "Ertelt , Eli"
      }
    ],
    "HOME SCHOOL / T 12:30": [
      {
        "position": 1,
        "name": "Sherman, Max (Maxwell)"
      }
    ],
    "INTERMEDIATE / F 4:00": [
      {
        "position": 1,
        "name": "Thomas, Eleanor"
      }
    ],
    "INTERMEDIATE / F 5:15": [
      {
        "position": 1,
        "name": "Newman, Valentina"
      },
      {
        "position": 2,
        "name": "Rub, Eleanor"
      },
      {
        "position": 3,
        "name": "Vitense, Erin"
      },
      {
        "position": 4,
        "name": "Munsell, Lilly"
      },
      {
        "position": 5,
        "name": "Santi, Mila"
      },
      {
        "position": 6,
        "name": "Toews, Isabelle"
      },
      {
        "position": 7,
        "name": "Brinda, Olivia"
      },
      {
        "position": 8,
        "name": "McKindles, Cecelia"
      }
    ],
    "INTERMEDIATE / M 4:00": [
      {
        "position": 1,
        "name": "Maciej, Evelyn"
      },
      {
        "position": 2,
        "name": "Joshi, Mihira"
      },
      {
        "position": 3,
        "name": "Wacker, Catriona"
      },
      {
        "position": 4,
        "name": "Amundson, Raelyn"
      },
      {
        "position": 5,
        "name": "Peschman , Mackenzie"
      },
      {
        "position": 6,
        "name": "Hoehne, Alexandra"
      },
      {
        "position": 7,
        "name": "Stickney, Ellie"
      },
      {
        "position": 8,
        "name": "Curb, Addison"
      },
      {
        "position": 9,
        "name": "Toews, Isabelle"
      },
      {
        "position": 10,
        "name": "Coey, Evelyn"
      },
      {
        "position": 11,
        "name": "Beauchamp, Maya"
      }
    ],
    "INTERMEDIATE / M 5:15": [
      {
        "position": 1,
        "name": "Meierbachtol , Charlotte"
      },
      {
        "position": 2,
        "name": "Broz, Olivia"
      },
      {
        "position": 3,
        "name": "Christensen , Noelle"
      },
      {
        "position": 4,
        "name": "Joshi, Mihira"
      },
      {
        "position": 5,
        "name": "Knight, Bayla"
      },
      {
        "position": 6,
        "name": "Kurth, Sophia"
      },
      {
        "position": 7,
        "name": "McShane, Taylor"
      },
      {
        "position": 8,
        "name": "Schill, Nora"
      },
      {
        "position": 9,
        "name": "Knight, Willa"
      },
      {
        "position": 10,
        "name": "Maciej, Evelyn"
      },
      {
        "position": 11,
        "name": "Amundson, Raelyn"
      },
      {
        "position": 12,
        "name": "Newman, Valentina"
      },
      {
        "position": 13,
        "name": "Munsell, Lilly"
      },
      {
        "position": 14,
        "name": "Schultz, Nora"
      },
      {
        "position": 15,
        "name": "Santi, Mila"
      },
      {
        "position": 16,
        "name": "Toews, Isabelle"
      },
      {
        "position": 17,
        "name": "Knutson, Olivia"
      }
    ],
    "INTERMEDIATE / T 4:00": [
      {
        "position": 1,
        "name": "Welu, Nora"
      },
      {
        "position": 2,
        "name": "Meehan, Simone"
      },
      {
        "position": 3,
        "name": "Quinn, Zoey"
      },
      {
        "position": 4,
        "name": "Curb, Addison"
      },
      {
        "position": 5,
        "name": "Toews, Isabelle"
      },
      {
        "position": 6,
        "name": "AASER, HAANIYA"
      },
      {
        "position": 7,
        "name": "Beauchamp, Maya"
      },
      {
        "position": 8,
        "name": "Taffe, Emerson"
      },
      {
        "position": 9,
        "name": "Doll, Leni"
      }
    ],
    "INTERMEDIATE / T 6:30": [
      {
        "position": 1,
        "name": "Johnson, Reagan"
      },
      {
        "position": 2,
        "name": "Meehan, Simone"
      },
      {
        "position": 3,
        "name": "Quinn, Zoey"
      },
      {
        "position": 4,
        "name": "Untiedt, Tessa"
      },
      {
        "position": 5,
        "name": "Jarvis, Marin"
      },
      {
        "position": 6,
        "name": "Paszkiewicz, Devin"
      },
      {
        "position": 7,
        "name": "Toews, Isabelle"
      },
      {
        "position": 8,
        "name": "Fitzpatrick, Nina"
      },
      {
        "position": 9,
        "name": "Cannizzaro, Madeline"
      },
      {
        "position": 10,
        "name": "Munsell, Lilly"
      },
      {
        "position": 11,
        "name": "Brinda, Olivia"
      },
      {
        "position": 12,
        "name": "Taffe, Emerson"
      }
    ],
    "INTERMEDIATE / TH 4:00": [
      {
        "position": 1,
        "name": "Wacker, Catriona"
      },
      {
        "position": 2,
        "name": "Christner, Mackenzie"
      },
      {
        "position": 3,
        "name": "Dukerschein, Aleah"
      },
      {
        "position": 4,
        "name": "DeVries, Reagan"
      },
      {
        "position": 5,
        "name": "Stickney, Ellie"
      },
      {
        "position": 6,
        "name": "Morris, Ada"
      },
      {
        "position": 7,
        "name": "Magnuson, Sophie"
      },
      {
        "position": 8,
        "name": "Rife, Isabelle"
      },
      {
        "position": 9,
        "name": "Meehan, Simone"
      },
      {
        "position": 10,
        "name": "Curb, Addison"
      },
      {
        "position": 11,
        "name": "Hoehne, Alexandra"
      },
      {
        "position": 12,
        "name": "Welu, Nora"
      },
      {
        "position": 13,
        "name": "Toews, Isabelle"
      },
      {
        "position": 14,
        "name": "Lieser, Lila"
      },
      {
        "position": 15,
        "name": "Beauchamp, Maya"
      }
    ],
    "INTERMEDIATE / TH 5:15": [
      {
        "position": 1,
        "name": "Kurth, Sophia"
      },
      {
        "position": 2,
        "name": "Tessier , Violet"
      },
      {
        "position": 3,
        "name": "Holman, Fiona"
      },
      {
        "position": 4,
        "name": "Christner, Mackenzie"
      },
      {
        "position": 5,
        "name": "Newman, Valentina"
      },
      {
        "position": 6,
        "name": "Holland, Isla"
      },
      {
        "position": 7,
        "name": "Paustenbach, Zoey"
      },
      {
        "position": 8,
        "name": "Nolan, Zoey"
      },
      {
        "position": 9,
        "name": "Johnson, Reagan"
      },
      {
        "position": 10,
        "name": "Hanson, Ada"
      },
      {
        "position": 11,
        "name": "Meehan, Simone"
      },
      {
        "position": 12,
        "name": "Santi, Mila"
      },
      {
        "position": 13,
        "name": "Seremet, Sadie"
      },
      {
        "position": 14,
        "name": "Parker, Laila"
      },
      {
        "position": 15,
        "name": "Bateman, Annabelle"
      },
      {
        "position": 16,
        "name": "Toews, Isabelle"
      }
    ],
    "INTERMEDIATE / TH 6:30": [
      {
        "position": 1,
        "name": "Danielson, Ella"
      },
      {
        "position": 2,
        "name": "Danielson, Emmy"
      },
      {
        "position": 3,
        "name": "Knight, Willa"
      },
      {
        "position": 4,
        "name": "Hamilton, Sophia"
      },
      {
        "position": 5,
        "name": "Newman, Valentina"
      },
      {
        "position": 6,
        "name": "Baez, Avery"
      },
      {
        "position": 7,
        "name": "Nolan, Zoey"
      },
      {
        "position": 8,
        "name": "Johnson, Reagan"
      },
      {
        "position": 9,
        "name": "Lillehaug, Reese"
      },
      {
        "position": 10,
        "name": "Untiedt, Tessa"
      },
      {
        "position": 11,
        "name": "Jarvis, Marin"
      },
      {
        "position": 12,
        "name": "Paszkiewicz, Devin"
      },
      {
        "position": 13,
        "name": "Toews, Isabelle"
      },
      {
        "position": 14,
        "name": "Munsell, Lilly"
      },
      {
        "position": 15,
        "name": "Brinda, Olivia"
      }
    ],
    "INTERMEDIATE / W 5:15": [
      {
        "position": 1,
        "name": "Bast, Ellie"
      },
      {
        "position": 2,
        "name": "Meehan, Simone"
      },
      {
        "position": 3,
        "name": "Quinn, Zoey"
      },
      {
        "position": 4,
        "name": "Santi, Mila"
      },
      {
        "position": 5,
        "name": "Paszkiewicz, Devin"
      },
      {
        "position": 6,
        "name": "Champion, Zoe"
      },
      {
        "position": 7,
        "name": "Amundson, Raelyn"
      }
    ],
    "INTERMEDIATE / W 6:30": [
      {
        "position": 1,
        "name": "Lau , Addison"
      },
      {
        "position": 2,
        "name": "AASER, HAANIYA"
      },
      {
        "position": 3,
        "name": "Danielson, Ella"
      },
      {
        "position": 4,
        "name": "Danielson, Emmy"
      },
      {
        "position": 5,
        "name": "Tessier , Violet"
      },
      {
        "position": 6,
        "name": "Hamilton, Sophia"
      },
      {
        "position": 7,
        "name": "Amundson, Raelyn"
      },
      {
        "position": 8,
        "name": "Newman, Valentina"
      },
      {
        "position": 9,
        "name": "Trible, Laila"
      },
      {
        "position": 10,
        "name": "Savat, Clara"
      },
      {
        "position": 11,
        "name": "Nolan, Zoey"
      },
      {
        "position": 12,
        "name": "Johnson, Reagan"
      },
      {
        "position": 13,
        "name": "Bucki, Aurora"
      },
      {
        "position": 14,
        "name": "Quinn, Zoey"
      },
      {
        "position": 15,
        "name": "Champion, Zoe"
      },
      {
        "position": 16,
        "name": "Lieser, Lila"
      }
    ],
    "MASTER / M 5:30": [
      {
        "position": 1,
        "name": "Hanson, Alice"
      },
      {
        "position": 2,
        "name": "Kamalapuram , Manvitha"
      },
      {
        "position": 3,
        "name": "Ditch, Sophie"
      },
      {
        "position": 4,
        "name": "McShane, Valerie"
      },
      {
        "position": 5,
        "name": "Becker, Evelyn"
      },
      {
        "position": 6,
        "name": "Totoritis-Searl, Tilly"
      },
      {
        "position": 7,
        "name": "Savage, Reagan"
      },
      {
        "position": 8,
        "name": "Grabek, Nora"
      },
      {
        "position": 9,
        "name": "Festler, Savannah"
      },
      {
        "position": 10,
        "name": "Thompson, Annabel"
      }
    ],
    "NINJA ZONE WHITE / F 6:30": [
      {
        "position": 1,
        "name": "Olson, Michael"
      },
      {
        "position": 2,
        "name": "Janzen, Micah"
      },
      {
        "position": 3,
        "name": "Mahrer, Remy"
      },
      {
        "position": 4,
        "name": "Rothstein , Garon"
      },
      {
        "position": 5,
        "name": "Trier, Fitz"
      },
      {
        "position": 6,
        "name": "Burke, Jameson"
      }
    ],
    "NINJA ZONE WHITE / M 4:00": [
      {
        "position": 1,
        "name": "Wacker, Beckett"
      },
      {
        "position": 2,
        "name": "Biagini, Vincent"
      },
      {
        "position": 3,
        "name": "Pfeffer, Eliab"
      },
      {
        "position": 4,
        "name": "Pfeffer, Enoch"
      },
      {
        "position": 5,
        "name": "Hawkinson, Leo"
      },
      {
        "position": 6,
        "name": "Grady, Brodyn"
      },
      {
        "position": 7,
        "name": "Cabalka, Finn"
      },
      {
        "position": 8,
        "name": "Wood, Walter"
      },
      {
        "position": 9,
        "name": "Wood, Lewis"
      },
      {
        "position": 10,
        "name": "Faltesek, Alice"
      },
      {
        "position": 11,
        "name": "Walsh, Kieran"
      },
      {
        "position": 12,
        "name": "Moitz, Billy"
      },
      {
        "position": 13,
        "name": "Belisle, Everett"
      },
      {
        "position": 14,
        "name": "Johnson, Wesley"
      }
    ],
    "NINJA ZONE WHITE / M 6:30": [
      {
        "position": 1,
        "name": "Hawkinson, Leo"
      },
      {
        "position": 2,
        "name": "Wood, Walter"
      },
      {
        "position": 3,
        "name": "Wood, Lewis"
      },
      {
        "position": 4,
        "name": "Mahrer, Remy"
      },
      {
        "position": 5,
        "name": "Smith, Rhett"
      },
      {
        "position": 6,
        "name": "Walker, Theodore"
      }
    ],
    "NINJA ZONE WHITE / S 10:15": [
      {
        "position": 1,
        "name": "Cabalka, Finn"
      },
      {
        "position": 2,
        "name": "Simmons, Aidan"
      },
      {
        "position": 3,
        "name": "Rothstein , Garon"
      },
      {
        "position": 4,
        "name": "Naughtin, Samuel"
      },
      {
        "position": 5,
        "name": "Bradley , Maxwell"
      },
      {
        "position": 6,
        "name": "Mahrer, Remy"
      },
      {
        "position": 7,
        "name": "Trier, Fitz"
      }
    ],
    "NINJA ZONE WHITE / T 6:30": [
      {
        "position": 1,
        "name": "Kelm, Jacob"
      },
      {
        "position": 2,
        "name": "Elliott, Brayden"
      },
      {
        "position": 3,
        "name": "Hughes, Ethan"
      },
      {
        "position": 4,
        "name": "Janzen, Micah"
      },
      {
        "position": 5,
        "name": "Hawkinson, Leo"
      },
      {
        "position": 6,
        "name": "Smith, Rhett"
      },
      {
        "position": 7,
        "name": "Walker, Theodore"
      }
    ],
    "NINJA ZONE WHITE / TH 4:00": [
      {
        "position": 1,
        "name": "Moitz, Billy"
      },
      {
        "position": 2,
        "name": "Jung, Owen"
      },
      {
        "position": 3,
        "name": "Hawkinson, Leo"
      },
      {
        "position": 4,
        "name": "King, Teddy"
      },
      {
        "position": 5,
        "name": "Trier, Fitz"
      }
    ],
    "NINJA ZONE YELLOW / GREEN (COMBO) / F 4:00": [
      {
        "position": 1,
        "name": "Danelius, Garrett"
      },
      {
        "position": 2,
        "name": "Doll, George"
      }
    ],
    "NINJA ZONE YELLOW / T 4:00": [
      {
        "position": 1,
        "name": "Doll, George"
      }
    ],
    "NINJA ZONE YELLOW / W 6:30": [
      {
        "position": 1,
        "name": "Wells, Roman"
      }
    ],
    "NZ - LIL NINJA / F 6:15": [
      {
        "position": 1,
        "name": "Rub, Ethan"
      },
      {
        "position": 2,
        "name": "Parsons, Leonard"
      },
      {
        "position": 3,
        "name": "Mahrer, Lincoln"
      },
      {
        "position": 4,
        "name": "Burke, Theodore"
      }
    ],
    "NZ - LIL NINJA / M 5:15": [
      {
        "position": 1,
        "name": "Smith, Otto"
      },
      {
        "position": 2,
        "name": "Westling, Charles"
      },
      {
        "position": 3,
        "name": "Ezuck, Lowyn"
      },
      {
        "position": 4,
        "name": "Gilbertson, Jacob"
      },
      {
        "position": 5,
        "name": "Jensen, Nolan"
      },
      {
        "position": 6,
        "name": "Margarit, Austin"
      },
      {
        "position": 7,
        "name": "Knutson, Axel"
      }
    ],
    "NZ - LIL NINJA / TH 5:15": [
      {
        "position": 1,
        "name": "Ormberg, Brecken"
      },
      {
        "position": 2,
        "name": "Lillehaug, Graham"
      },
      {
        "position": 3,
        "name": "Abernathey, Dexter"
      },
      {
        "position": 4,
        "name": "Jochims, Bruce"
      },
      {
        "position": 5,
        "name": "King, Bobby"
      },
      {
        "position": 6,
        "name": "Ezuck, Lowyn"
      },
      {
        "position": 7,
        "name": "Madgett, Wells"
      },
      {
        "position": 8,
        "name": "Westling, Charles"
      },
      {
        "position": 9,
        "name": "Uchtman, Cooper"
      },
      {
        "position": 10,
        "name": "Jensen, Nolan"
      },
      {
        "position": 11,
        "name": "Margarit, Austin"
      },
      {
        "position": 12,
        "name": "Saffrin, Marcus"
      },
      {
        "position": 13,
        "name": "Strey-Millstone, Finley"
      },
      {
        "position": 14,
        "name": "Grein, Jemuel"
      },
      {
        "position": 15,
        "name": "Smith, Otto"
      },
      {
        "position": 16,
        "name": "Mahrer, Lincoln"
      }
    ],
    "REC TEAM PRACTICE/ S 12:30pm": [
      {
        "position": 1,
        "name": "Shah, Pari"
      },
      {
        "position": 2,
        "name": "Spronk, Vivian"
      },
      {
        "position": 3,
        "name": "McShane, Valerie"
      }
    ]
  },
  "classes_with_openings": [
    {
      "name": "2s - TALENTED 2s / F 5:15",
      "classId": "3854",
      "open_spots": 4,
      "month": "current"
    },
    {
      "name": "2s - TALENTED 2s / M 9:15",
      "classId": "3850",
      "open_spots": 1,
      "month": "current"
    },
    {
      "name": "2s - TALENTED 2s / S 10:15",
      "classId": "3857",
      "open_spots": 1,
      "month": "current"
    },
    {
      "name": "2s - TALENTED 2s / T 11:15",
      "classId": "3851",
      "open_spots": 1,
      "month": "current"
    },
    {
      "name": "3/4s - TREMENDOUS 3s/FABULOUS 4s (COMBO) TH 9:15",
      "classId": "3870",
      "open_spots": 1,
      "month": "current"
    },
    {
      "name": "3/4s - TREMENDOUS 3s/FABULOUS 4s (COMBO) W 11:15",
      "classId": "3867",
      "open_spots": 3,
      "month": "current"
    },
    {
      "name": "ADVANCED / T 6:30",
      "classId": "3912",
      "open_spots": 2,
      "month": "current"
    },
    {
      "name": "ADVANCED / W 4:00",
      "classId": "3943",
      "open_spots": 1,
      "month": "current"
    },
    {
      "name": "ADVANCED / W 5:15",
      "classId": "3913",
      "open_spots": 3,
      "month": "current"
    },
    {
      "name": "ADVANCED BEGINNER / S 11:30",
      "classId": "3955",
      "open_spots": 4,
      "month": "current"
    },
    {
      "name": "ADVANCED BEGINNER /F 6:30",
      "classId": "3898",
      "open_spots": 1,
      "month": "current"
    },
    {
      "name": "BEGINNER / F 4:00",
      "classId": "3885",
      "open_spots": 1,
      "month": "current"
    },
    {
      "name": "BOYS ADV. BEGINNER /INTERMEDIATE (COMBO) / F 5:15",
      "classId": "3922",
      "open_spots": 4,
      "month": "current"
    },
    {
      "name": "BOYS ADV. BEGINNER /INTERMEDIATE (COMBO) / W 6:30",
      "classId": "3921",
      "open_spots": 2,
      "month": "current"
    },
    {
      "name": "HOME SCHOOL / W 12:30",
      "classId": "3938",
      "open_spots": 2,
      "month": "current"
    },
    {
      "name": "INTERMEDIATE / F 6:30",
      "classId": "3945",
      "open_spots": 1,
      "month": "current"
    },
    {
      "name": "MASTER / W 4:00",
      "classId": "3917",
      "open_spots": 1,
      "month": "current"
    },
    {
      "name": "NINJA ZONE GREEN / TH 5:15",
      "classId": "3936",
      "open_spots": 4,
      "month": "current"
    },
    {
      "name": "NZ - LIL NINJA / F 10:15",
      "classId": "3925",
      "open_spots": 1,
      "month": "current"
    },
    {
      "name": "2s - TALENTED 2s / W 6:15",
      "classId": "3853",
      "open_spots": 1,
      "month": "March"
    },
    {
      "name": "BEGINNER / W 6:30",
      "classId": "3941",
      "open_spots": 1,
      "month": "March"
    },
    {
      "name": "BOYS BEGINNER / M 5:15",
      "classId": "3918",
      "open_spots": 1,
      "month": "March"
    },
    {
      "name": "BOYS BEGINNER / TH 6:30",
      "classId": "3920",
      "open_spots": 1,
      "month": "March"
    },
    {
      "name": "INTERMEDIATE / S 9:00",
      "classId": "3909",
      "open_spots": 1,
      "month": "March"
    }
  ],
  "action_needed": [
    {
      "name": "INTERMEDIATE / TH 6:30",
      "classId": "3906",
      "open_spots": 1,
      "waiting": 15,
      "enrolled": 7
    }
  ],
  "camps_with_openings": [
    {
      "name": "3/23-3/27 Jungle Safari Camp FULL DAY 8:30am - 4:00pm",
      "open_spots": 5,
      "waitlist": 0,
      "priority": false
    },
    {
      "name": "3/23-3/27 Jungle Safari Camp HALF DAY 8:30am - 12:15pm",
      "open_spots": 5,
      "waitlist": 0,
      "priority": false
    },
    {
      "name": "3/23-3/27 Jungle Safari Camp HALF DAY 12:15pm - 4:00pm",
      "open_spots": 5,
      "waitlist": 0,
      "priority": false
    },
    {
      "name": "3/30 - 4/3 All Around the World Camp HALF DAY 8:30am - 12:15pm",
      "open_spots": 4,
      "waitlist": 0,
      "priority": false
    },
    {
      "name": "3/30 - 4/3 All Around the World Camp FULL DAY 8:30am - 4:00pm",
      "open_spots": 9,
      "waitlist": 0,
      "priority": false
    },
    {
      "name": "3/30 - 4/3 All Around the World Camp HALF DAY 12:15pm - 4:00pm",
      "open_spots": 5,
      "waitlist": 0,
      "priority": false
    },
    {
      "name": "5/8 Spring Into Nature Camp HALF DAY 8:30am - 12:15pm",
      "open_spots": 4,
      "waitlist": 0,
      "priority": false
    },
    {
      "name": "5/8 Spring Into Nature Camp FULL DAY 8:30am - 4:00pm",
      "open_spots": 8,
      "waitlist": 0,
      "priority": false
    },
    {
      "name": "5/8 Spring Into Nature Camp HALF DAY 12:15pm - 4:00pm",
      "open_spots": 4,
      "waitlist": 0,
      "priority": false
    },
    {
      "name": "Friday Fun Days!",
      "open_spots": 14,
      "waitlist": 0,
      "priority": false
    },
    {
      "name": "6/8-6/11 Carnival Camp HALF DAY 12:15 pm - 4:00pm - $240",
      "open_spots": 5,
      "waitlist": 0,
      "priority": false
    },
    {
      "name": "6/8-6/11 Carnival Camp HALF DAY 8:30am - 12:15 pm $240",
      "open_spots": 3,
      "waitlist": 0,
      "priority": false
    },
    {
      "name": "6/15-6/18 Color Explosion Camp HALF DAY 12:15 pm - 4:00pm - $240",
      "open_spots": 2,
      "waitlist": 0,
      "priority": false
    },
    {
      "name": "6/15-6/18 Color Explosion Camp HALF DAY 8:30am - 12:15 pm $240",
      "open_spots": 1,
      "waitlist": 0,
      "priority": false
    },
    {
      "name": "6/22-6/25 Fairy Tale Fantasy Camp FULL DAY 8:30am - 4:00 pm $420",
      "open_spots": 1,
      "waitlist": 0,
      "priority": false
    },
    {
      "name": "6/22-6/25 Fairy Tale Fantasy Camp HALF DAY 12:15 pm - 4:00pm - $240",
      "open_spots": 4,
      "waitlist": 0,
      "priority": false
    },
    {
      "name": "6/22-6/25 Fairy Tale Fantasy Camp HALF DAY 8:30am - 12:15 pm $240",
      "open_spots": 5,
      "waitlist": 0,
      "priority": false
    },
    {
      "name": "6/29-7/2 Planet Earth Week Camp FULL DAY 8:30am - 4:00 pm $420",
      "open_spots": 7,
      "waitlist": 0,
      "priority": false
    },
    {
      "name": "6/29-7/2 Planet Earth Week Camp HALF DAY 12:15 pm - 4:00pm - $240",
      "open_spots": 5,
      "waitlist": 0,
      "priority": false
    },
    {
      "name": "6/29-7/2 Planet Earth Week Camp HALF DAY 8:30am - 12:15 pm $240",
      "open_spots": 3,
      "waitlist": 0,
      "priority": false
    },
    {
      "name": "7/6-7/9 Mini Architects Camp HALF DAY 12:15 pm - 4:00pm - $240",
      "open_spots": 5,
      "waitlist": 0,
      "priority": false
    },
    {
      "name": "7/6-7/9 Mini Architects Camp FULL DAY 8:30am - 4:00 pm $420",
      "open_spots": 7,
      "waitlist": 0,
      "priority": false
    },
    {
      "name": "7/13- 7/16 Treasure Hunters Camp FULL DAY 8:30am - 4:00 pm $420",
      "open_spots": 3,
      "waitlist": 0,
      "priority": false
    },
    {
      "name": "7/13- 7/16 Treasure Hunters Camp HALF DAY 12:15 pm - 4:00pm - $240",
      "open_spots": 3,
      "waitlist": 0,
      "priority": false
    },
    {
      "name": "7/13- 7/16 Treasure Hunters Camp HALF DAY 8:30am - 12:15 pm $240",
      "open_spots": 3,
      "waitlist": 0,
      "priority": false
    },
    {
      "name": "7/20-7/23 Winter in July Camp HALF DAY 12:15 pm - 4:00pm - $240",
      "open_spots": 5,
      "waitlist": 0,
      "priority": false
    },
    {
      "name": "7/20-7/23 Winter in July Camp FULL DAY 8:30am - 4:00 pm $420",
      "open_spots": 4,
      "waitlist": 0,
      "priority": false
    },
    {
      "name": "7/20-7/23 Winter in July Camp HALF DAY 8:30am - 12:15 pm $240",
      "open_spots": 4,
      "waitlist": 0,
      "priority": false
    },
    {
      "name": "7/27-7/30 Storybook Adventures Camp HALF DAY 8:30am - 12:15 pm $240",
      "open_spots": 3,
      "waitlist": 0,
      "priority": false
    },
    {
      "name": "7/27-7/30 Storybook Adventures Camp FULL DAY 8:30am - 4:00 pm $420",
      "open_spots": 7,
      "waitlist": 0,
      "priority": false
    },
    {
      "name": "7/27-7/30 Storybook Adventures Camp HALF DAY 12:15 pm - 4:00pm - $240",
      "open_spots": 5,
      "waitlist": 0,
      "priority": false
    },
    {
      "name": "8/3-8/6 Beach Party Camp FULL DAY 8:30am - 4:00 pm $420",
      "open_spots": 1,
      "waitlist": 0,
      "priority": false
    },
    {
      "name": "8/3-8/6 Beach Party Camp HALF DAY 12:15 pm - 4:00pm - $240",
      "open_spots": 5,
      "waitlist": 0,
      "priority": false
    },
    {
      "name": "8/10-8/13 Weather Wonders Camp HALF DAY 12:15 pm - 4:00pm - $240",
      "open_spots": 3,
      "waitlist": 0,
      "priority": false
    },
    {
      "name": "8/17-8/20 Mini Chefs Camp HALF DAY 12:15 pm - 4:00pm - $240",
      "open_spots": 4,
      "waitlist": 0,
      "priority": false
    },
    {
      "name": "8/31-9/3 Glow-in-the-Dark Camp HALF DAY 12:15 pm - 4:00pm - $240",
      "open_spots": 4,
      "waitlist": 0,
      "priority": false
    },
    {
      "name": "8/31-9/3 Glow-in-the-Dark Camp HALF DAY 8:30am - 12:15 pm $240",
      "open_spots": 4,
      "waitlist": 0,
      "priority": false
    }
  ],
  "camps_with_waitlist": [
    {
      "name": "8/24-8/27 Bubble Bonanza Camp FULL DAY 8:30am - 4:00 pm $420",
      "waitlist": 15,
      "enrolled": 12
    },
    {
      "name": "8/24-8/27 Bubble Bonanza Camp HALF DAY 8:30am - 12:15 pm $240",
      "waitlist": 3,
      "enrolled": 3
    },
    {
      "name": "8/10-8/13 Weather Wonders Camp FULL DAY 8:30am - 4:00 pm $420",
      "waitlist": 2,
      "enrolled": 12
    },
    {
      "name": "3/6 Dream Job Gymnastics Camp FULL DAY 8:30am - 4:00pm",
      "waitlist": 1,
      "enrolled": 13
    },
    {
      "name": "6/8-6/11 Carnival Camp FULL DAY 8:30am - 4:00 pm $420",
      "waitlist": 1,
      "enrolled": 10
    },
    {
      "name": "8/17-8/20 Mini Chefs Camp HALF DAY 8:30am - 12:15 pm $240",
      "waitlist": 1,
      "enrolled": 4
    },
    {
      "name": "8/24-8/27 Bubble Bonanza Camp HALF DAY 12:15 pm - 4:00pm - $240",
      "waitlist": 1,
      "enrolled": 3
    },
    {
      "name": "8/31-9/3 Glow-in-the-Dark Camp FULL DAY 8:30am - 4:00 pm $420",
      "waitlist": 1,
      "enrolled": 10
    }
  ],
  "next_month_start_date": "March 2, 2026"
}